stache_ai_documents/__init__.py
stache_ai_documents/docx.py
stache_ai_documents/epub.py
stache_ai_documents/pptx.py
stache_ai_documents-0.1.0.dist-info/METADATA
stache_ai_documents-0.1.0.dist-info/WHEEL
stache_ai_documents-0.1.0.dist-info/entry_points.txt
stache_ai_documents-0.1.0.dist-info/top_level.txt
stache_ai_documents-0.1.0.dist-info/RECORD
